[{"id":"a33f4845-c0aa-4b22-a80a-c2d93a7f0bbd","userFirstName":"Karel","userLastName":"Denidge","birthday":"1967-08-11","phoneNumber":"+351 937 509 6272"},
  {"id":"1be9ed87-887a-4e67-827f-ca111969ae1c","userFirstName":"Bernardo","userLastName":"Stidston","birthday":"2002-04-03","phoneNumber":"+86 227 754 0801"},
  {"id":"47c67417-6fb2-490f-aa7e-e9a0c34d1489","userFirstName":"Eachelle","userLastName":"Geroldo","birthday":"1999-06-27","phoneNumber":"+86 680 517 0658"},
  {"id":"5f397bac-1977-47a9-8d4a-d8f9a5c6b1ba","userFirstName":"Henry","userLastName":"Mitchard","birthday":"1982-08-26","phoneNumber":"+7 976 279 7522"},
  {"id":"7440dc5f-6d3f-4768-a48c-629a380e0276","userFirstName":"Fernanda","userLastName":"Gemson","birthday":"1973-07-21","phoneNumber":"+351 837 986 9692"},
  {"id":"99143279-373a-4808-8e18-b5090f14d895","userFirstName":"Mollee","userLastName":"Moakes","birthday":"1994-03-31","phoneNumber":"+48 202 595 9634"},
  {"id":"1dc21d97-40ab-4d99-a88d-0dafb20f55b1","userFirstName":"Gardener","userLastName":"Gambles","birthday":"2011-03-16","phoneNumber":"+55 873 782 1629"},
  {"id":"499f5d12-a506-4d5e-9c33-84220f314f89","userFirstName":"Josiah","userLastName":"Van den Broek","birthday":"2012-11-15","phoneNumber":"+7 382 272 8041"},
  {"id":"017860da-047b-4d26-a2df-b53379766225","userFirstName":"Julian","userLastName":"Wankel","birthday":"1991-10-22","phoneNumber":"+7 320 650 0834"},
  {"id":"77d35000-cb71-4225-ac80-52825059243e","userFirstName":"Antin","userLastName":"Casbon","birthday":"1986-01-23","phoneNumber":"+86 509 123 9443"},
  {"id":"ab8186db-cde3-4206-ae85-e6676fa80e12","userFirstName":"Chick","userLastName":"Allington","birthday":"1963-01-17","phoneNumber":"+86 750 664 7901"},
  {"id":"3426238a-afc9-42e3-929f-5c2c9860f97f","userFirstName":"Zebadiah","userLastName":"Doey","birthday":"1950-05-21","phoneNumber":"+33 220 789 6994"},
  {"id":"649f2ed5-7a84-46bc-84c9-6a87f65b7c9e","userFirstName":"Chet","userLastName":"Keslake","birthday":"2011-01-02","phoneNumber":"+30 373 405 7800"},
  {"id":"87ed0030-c966-4716-b15c-f324f49b6bbe","userFirstName":"Ammamaria","userLastName":"Easby","birthday":"1970-08-30","phoneNumber":"+62 510 529 3410"},
  {"id":"4485167b-f1f6-474a-883d-2ca3ee3fb2a4","userFirstName":"Freddy","userLastName":"Yeoman","birthday":"1976-10-03","phoneNumber":"+976 750 912 9517"},
  {"id":"cc1e52e1-1c0c-43d2-be07-bad23ec7b558","userFirstName":"Crista","userLastName":"Heatlie","birthday":"1994-05-18","phoneNumber":"+33 377 667 3467"},
  {"id":"25f775ec-65c1-4a72-a65c-a410fbae0294","userFirstName":"Kristien","userLastName":"Davidovics","birthday":"1976-08-03","phoneNumber":"+86 335 746 2582"},
  {"id":"3966ac00-0ad7-428e-bf0f-b815d557a644","userFirstName":"Ramsay","userLastName":"Maceur","birthday":"1952-04-14","phoneNumber":"+86 505 968 7960"},
  {"id":"96072729-79cd-430a-a796-703cdb16338d","userFirstName":"Tallia","userLastName":"Frake","birthday":"1998-09-15","phoneNumber":"+62 602 420 4167"},
  {"id":"07e73f01-ea2b-49ea-abc6-c62c26e1c2d2","userFirstName":"Algernon","userLastName":"Scoyles","birthday":"1958-12-09","phoneNumber":"+234 198 534 8776"},
  {"id":"b50f11cb-01dd-40a3-9117-db8631975170","userFirstName":"Jasmine","userLastName":"Hambleton","birthday":"1997-02-14","phoneNumber":"+62 953 266 2669"},
  {"id":"9f377313-41b7-436d-a534-8deb73a1c0da","userFirstName":"Ulla","userLastName":"McKeeman","birthday":"1964-10-31","phoneNumber":"+62 853 696 5014"},
  {"id":"f439058a-1d2e-4fb9-bb22-97570ca01c99","userFirstName":"Sancho","userLastName":"Beche","birthday":"2014-01-24","phoneNumber":"+86 579 628 6283"},
  {"id":"da1f9ee9-885f-45a9-b713-ae5fc9612602","userFirstName":"Nichols","userLastName":"Redwin","birthday":"1998-10-10","phoneNumber":"+420 783 518 3620"},
  {"id":"4afc8445-2103-437d-84ef-2491af8c17cf","userFirstName":"Saundra","userLastName":"Robjant","birthday":"2009-04-26","phoneNumber":"+86 841 240 6251"},
  {"id":"512289fd-9d67-42cd-8475-2d676bfec537","userFirstName":"Nelle","userLastName":"Trewhitt","birthday":"1993-07-24","phoneNumber":"+84 424 883 4077"},
  {"id":"bd806bbb-3212-40a0-a46d-f7c3664e8f27","userFirstName":"Clarie","userLastName":"Georgeou","birthday":"1962-09-16","phoneNumber":"+62 964 647 2696"},
  {"id":"129a6890-2cf9-46ec-ad11-2819337426e6","userFirstName":"Frannie","userLastName":"Raw","birthday":"1960-02-01","phoneNumber":"+54 744 100 7410"},
  {"id":"6b761ae4-60a3-4456-a1a5-3b196e9423d0","userFirstName":"Rozamond","userLastName":"Upham","birthday":"2005-09-14","phoneNumber":"+62 376 290 6555"},
  {"id":"ac6ac994-b077-4916-9ce6-59f3e069e1a7","userFirstName":"Allene","userLastName":"Pinock","birthday":"2010-06-23","phoneNumber":"+47 762 187 5298"},
  {"id":"486c6112-37d9-4d89-ab34-9b12cc832642","userFirstName":"Leo","userLastName":"Ambler","birthday":"1990-12-05","phoneNumber":"+86 975 380 3031"},
  {"id":"5c3c4e1b-28b3-49c7-9848-03d93771cbbf","userFirstName":"Waiter","userLastName":"Blessed","birthday":"1968-11-16","phoneNumber":"+86 569 859 0851"},
  {"id":"8911ffee-bc54-4a25-99c6-5440bc9a680e","userFirstName":"Kayne","userLastName":"Klais","birthday":"1984-09-29","phoneNumber":"+86 898 660 5453"},
  {"id":"9021c175-05ca-46ec-b320-211f0da29960","userFirstName":"Jeramie","userLastName":"Harp","birthday":"1952-09-22","phoneNumber":"+7 384 640 1793"},
  {"id":"73a89b52-2e32-41de-a17e-84cdf843539f","userFirstName":"Winnie","userLastName":"Lynas","birthday":"1969-10-23","phoneNumber":"+62 335 453 7811"},
  {"id":"add8a690-cc96-43bb-9040-efca80e1df59","userFirstName":"Dominica","userLastName":"Gimblett","birthday":"1987-09-10","phoneNumber":"+62 320 432 0202"},
  {"id":"962ad8db-d410-45dc-b300-47ee2e473821","userFirstName":"Roseann","userLastName":"Ravillas","birthday":"1987-02-16","phoneNumber":"+55 115 150 9086"},
  {"id":"e1e20099-7b15-457e-9cba-77b600cecdf4","userFirstName":"Hallsy","userLastName":"Hopkynson","birthday":"1989-03-19","phoneNumber":"+86 948 900 0906"},
  {"id":"f0c9c97c-27ee-4887-896d-a87f065118b3","userFirstName":"Josefa","userLastName":"Fiddian","birthday":"2011-07-26","phoneNumber":"+51 293 175 0421"},
  {"id":"ad731e29-c133-4c5f-b1f3-20bf8d6f8a95","userFirstName":"Beverlee","userLastName":"Boaler","birthday":"1998-09-10","phoneNumber":"+63 260 838 6666"},
  {"id":"53ec1eeb-85e8-4c3b-8fee-b0b0be9c3391","userFirstName":"Maxie","userLastName":"Stennings","birthday":"1976-06-15","phoneNumber":"+255 470 493 5500"},
  {"id":"d0c4dc12-f9e4-4470-abd7-577beca9ddff","userFirstName":"Nil","userLastName":"Zoppo","birthday":"1992-06-06","phoneNumber":"+63 271 117 6065"},
  {"id":"6d8b44d6-4818-467b-8a6a-99154d4a2dfc","userFirstName":"Simone","userLastName":"Jewess","birthday":"1985-04-24","phoneNumber":"+86 808 446 0194"},
  {"id":"5e9e5e90-378d-4743-bb11-09a81089ca24","userFirstName":"Lorrayne","userLastName":"Twede","birthday":"1968-02-16","phoneNumber":"+86 422 975 7460"},
  {"id":"b3e47ff5-d048-4b07-89c6-7d6c9c48bb7b","userFirstName":"Loralyn","userLastName":"De Bruyne","birthday":"2010-07-28","phoneNumber":"+62 343 389 5976"}]